config/settings.py
config/urls.py
huscy/project_storage/__init__.py
huscy/project_storage/models.py
tests/test_assert_true.py
huscy.project_storage-0.1.0a0.dist-info/LICENSE
huscy.project_storage-0.1.0a0.dist-info/METADATA
huscy.project_storage-0.1.0a0.dist-info/WHEEL
huscy.project_storage-0.1.0a0.dist-info/top_level.txt
huscy.project_storage-0.1.0a0.dist-info/RECORD
